pictobloxindexer/__init__.py
pictobloxindexer-1.0.dist-info/LICENSE
pictobloxindexer-1.0.dist-info/METADATA
pictobloxindexer-1.0.dist-info/WHEEL
pictobloxindexer-1.0.dist-info/top_level.txt
pictobloxindexer-1.0.dist-info/RECORD
