Metadata-Version: 2.1
Name: pictobloxindexer
Version: 1.0
Summary: Mark is an AI voice activated robot.
Home-page: https://github.com/ProjectMarkLLM/pb-pip-test#readme
Author: MarkLLM
Author-email: projectmark.ai@gmail.com
Requires-Python: >=3.8
License-File: LICENSE
Requires-Dist: requests >=2.26.0
Requires-Dist: typing-extensions
